cpnpy/__init__.py
cpnpy/home.py
cpnpy/meta.py
cpnpy/analysis/__init__.py
cpnpy/analysis/analyzer.py
cpnpy/analysis/reachability.py
cpnpy/analysis/scc.py
cpnpy/cpn/__init__.py
cpnpy/cpn/colorsets.py
cpnpy/cpn/cpn_imp.py
cpnpy/cpn/exporter.py
cpnpy/cpn/importer.py
cpnpy/discovery/__init__.py
cpnpy/discovery/traditional.py
cpnpy/hcpn/__init__.py
cpnpy/hcpn/hcpn_imp.py
cpnpy/interface/__init__.py
cpnpy/interface/draw.py
cpnpy/interface/import_export.py
cpnpy/interface/simulation.py
cpnpy/simulation/__init__.py
cpnpy/simulation/ocel_simu.py
cpnpy/util/__init__.py
cpnpy/util/extr_min_xml_struct.py
cpnpy/util/rv_to_stri.py
cpnpy/util/simp_guard.py
cpnpy/util/strip_timing.py
cpnpy/util/svg_parser.py
cpnpy/util/conversion/__init__.py
cpnpy/util/conversion/cpn_xml_to_json.py
cpnpy/util/conversion/json_to_cpn_xml.py
cpnpy/util/conversion/llm_json_fixing.py
cpnpy/visualization/__init__.py
cpnpy/visualization/hcpn.py
cpnpy/visualization/visualizer.py
cpnpy-0.2.1.dist-info/licenses/LICENSE
cpnpy-0.2.1.dist-info/METADATA
cpnpy-0.2.1.dist-info/WHEEL
cpnpy-0.2.1.dist-info/top_level.txt
cpnpy-0.2.1.dist-info/RECORD
