Metadata-Version: 2.4
Name: cpnpy
Version: 0.2.1
Summary: A Python-based library designed to simulate Colored Petri Nets (CPNs) with optional time semantics.
Home-page: https://github.com/fit-alessandro-berti/cpn-py
Author: Alessandro Berti
Author-email: a.berti@pads.rwth-aachen.de
License: GPL-3.0
Classifier: Programming Language :: Python :: 3
Classifier: License :: OSI Approved :: GNU General Public License v3 (GPLv3)
Classifier: Operating System :: OS Independent
Classifier: Topic :: Scientific/Engineering
Requires-Python: >=3.6
License-File: LICENSE
Requires-Dist: pm4py
Requires-Dist: jsonschema
Requires-Dist: simpy
Dynamic: author
Dynamic: author-email
Dynamic: classifier
Dynamic: description
Dynamic: description-content-type
Dynamic: home-page
Dynamic: license
Dynamic: license-file
Dynamic: requires-dist
Dynamic: requires-python
Dynamic: summary
